dictf/__init__.py
dictf/dictf.py
dictf-1.0.0.dist-info/LICENSE
dictf-1.0.0.dist-info/METADATA
dictf-1.0.0.dist-info/WHEEL
dictf-1.0.0.dist-info/top_level.txt
dictf-1.0.0.dist-info/RECORD
