Metadata-Version: 2.1
Name: dictf
Version: 1.0.0
Summary: An extended Python dict implementation that supports multiple key selection with a pretty syntax.
Author-email: Eric Mendes <ericvelasco.2000@gmail.com>
Maintainer-email: Eric Mendes <ericvelasco.2000@gmail.com>
License: Copyright (c) 2016 The Python Packaging Authority (PyPA)
Project-URL: Homepage, https://github.com/Eric-Mendes/dictf
Project-URL: Bug Reports, https://github.com/Eric-Mendes/dictf/issues
Project-URL: Source, https://github.com/Eric-Mendes/dictf
Keywords: data structures,data,dict,map
Classifier: Development Status :: 5 - Production/Stable
Classifier: Intended Audience :: Developers
Classifier: Topic :: Software Development
Classifier: License :: OSI Approved :: MIT License
Classifier: Programming Language :: Python :: 3
Classifier: Programming Language :: Python :: 3.8
Classifier: Programming Language :: Python :: 3.9
Classifier: Programming Language :: Python :: 3.10
Classifier: Programming Language :: Python :: 3.11
Classifier: Programming Language :: Python :: 3 :: Only
Requires-Python: >=3.8
License-File: LICENSE
Provides-Extra: dev
Requires-Dist: black ; extra == 'dev'
